remotsylib/__init__.py
remotsylib/api.py
remotsylib-0.0.2.dist-info/LICENSE.txt
remotsylib-0.0.2.dist-info/METADATA
remotsylib-0.0.2.dist-info/WHEEL
remotsylib-0.0.2.dist-info/top_level.txt
remotsylib-0.0.2.dist-info/RECORD
