Metadata-Version: 2.1
Name: remotsylib
Version: 0.0.2
Summary: A Remotsy python lib for use the Restfull API
Home-page: https://github.com/jorgecis/remotsylib
Author: Jorge Cisneros
Author-email: jorge@remotsy.com
License: UNKNOWN
Keywords: Remotsy infrared remote control smarthome
Platform: UNKNOWN
Classifier: Development Status :: 4 - Beta
Classifier: Intended Audience :: Developers
Classifier: Topic :: Software Development :: Build Tools
Classifier: License :: OSI Approved :: MIT License
Classifier: Programming Language :: Python :: 2
Classifier: Programming Language :: Python :: 2.7
Classifier: Programming Language :: Python :: 3.5
Classifier: Programming Language :: Python :: 3.6
Classifier: Programming Language :: Python :: 3.7
